woflo/__init__.py
woflo/runners/__init__.py
woflo/runners/base.py
woflo/runners/multiprocess.py
woflo/runners/sequential.py
woflo/task/__init__.py
woflo/task/__task.py
woflo/util/__init__.py
woflo/util/logger.py
woflo-0.8.2.dist-info/LICENSE
woflo-0.8.2.dist-info/WHEEL
woflo-0.8.2.dist-info/METADATA
woflo-0.8.2.dist-info/RECORD
