Metadata-Version: 2.1
Name: woflo
Version: 0.8.2
Summary: Python local-first no-bloat task orchestration framework 
Home-page: https://github.com/petereon/woflo
License: MIT
Keywords: python
Author: Peter Vyboch
Author-email: pvyboch1@gmail.com
Requires-Python: >=3.7.8,<4.0.0
Classifier: License :: OSI Approved :: MIT License
Classifier: Programming Language :: Python :: 3
Classifier: Programming Language :: Python :: 3.8
Classifier: Programming Language :: Python :: 3.9
Classifier: Programming Language :: Python :: 3.10
Classifier: Programming Language :: Python :: 3
Requires-Dist: multiprocess (>=0.70.13,<0.71.0)
Project-URL: Repository, https://github.com/petereon/woflo
